essentialdb/__init__.py
essentialdb/collection.py
essentialdb/essential_db.py
essentialdb/essential_index.py
essentialdb/essential_oid.py
essentialdb/essential_serializer.py
essentialdb/essential_shell.py
essentialdb/keys.py
essentialdb/local_collection.py
essentialdb/query_filter.py
essentialdb-0.7.1.dist-info/DESCRIPTION.rst
essentialdb-0.7.1.dist-info/METADATA
essentialdb-0.7.1.dist-info/RECORD
essentialdb-0.7.1.dist-info/WHEEL
essentialdb-0.7.1.dist-info/metadata.json
essentialdb-0.7.1.dist-info/top_level.txt
