Metadata-Version: 2.0
Name: essentialdb
Version: 0.7.1
Summary: EssentialDB - pure Python document database.
Home-page: https://github.com/shane-mason/essentialdb
Author: Shane C Mason
Author-email: shane.c.mason@gmail.com
License: MIT
Keywords: database
Platform: UNKNOWN
Classifier: Development Status :: 4 - Beta
Classifier: Intended Audience :: Developers
Classifier: Topic :: Software Development :: Build Tools
Classifier: License :: OSI Approved :: MIT License
Classifier: Programming Language :: Python :: 3
Classifier: Programming Language :: Python :: 3.3
Classifier: Programming Language :: Python :: 3.4
Classifier: Programming Language :: Python :: 3.5
Classifier: Programming Language :: Python :: 3.6
Provides-Extra: dev
Requires-Dist: check-manifest; extra == 'dev'
Provides-Extra: test
Requires-Dist: coverage; extra == 'test'
